README.md
setup.py
miniworlds_physics/__init__.py
miniworlds_physics/actor_physics.py
miniworlds_physics/physics_world.py
miniworlds_physics/physics_world_connector.py
miniworlds_physics/physics_world_event_manager.py
miniworlds_physics/physics_world_position_manager.py
miniworlds_physics.egg-info/PKG-INFO
miniworlds_physics.egg-info/SOURCES.txt
miniworlds_physics.egg-info/dependency_links.txt
miniworlds_physics.egg-info/requires.txt
miniworlds_physics.egg-info/top_level.txt